Metadata-Version: 2.1
Name: static-code-checker
Version: 1.0.0
Summary: Test code against each other for classes
Home-page: https://github.com/gadzygadz/CodeChecker
Author: Jake Gadaleta
Author-email: jake.gads@gmail.com
License: MIT
Platform: UNKNOWN
Classifier: License :: OSI Approved :: MIT License
Classifier: Programming Language :: Python :: 3
Classifier: Programming Language :: Python :: 3.7
